pyHomee/__init__.py
pyHomee/const.py
pyHomee/model.py
pyHomee/py.typed
pyhomee-1.3.8.dist-info/licenses/LICENSE
pyhomee-1.3.8.dist-info/METADATA
pyhomee-1.3.8.dist-info/WHEEL
pyhomee-1.3.8.dist-info/top_level.txt
pyhomee-1.3.8.dist-info/RECORD
