Metadata-Version: 2.4
Name: pyHomee
Version: 1.3.8
Summary: a python library to interact with homee
Author: Taraman17
License-Expression: MIT
Project-URL: Repository, https://github.com/Taraman17/pyHomee
Classifier: Programming Language :: Python :: 3
Classifier: Operating System :: OS Independent
Requires-Python: >=3.11
License-File: LICENSE
Requires-Dist: aiohttp>=3.11
Requires-Dist: websockets>=13
Dynamic: license-file
